cayennelpp/__init__.py
cayennelpp/lpp_data.py
cayennelpp/lpp_frame.py
cayennelpp/lpp_type.py
cayennelpp/lpp_util.py
micropython_pycayennelpp-2.4.0.dist-info/LICENSE
micropython_pycayennelpp-2.4.0.dist-info/METADATA
micropython_pycayennelpp-2.4.0.dist-info/WHEEL
micropython_pycayennelpp-2.4.0.dist-info/top_level.txt
micropython_pycayennelpp-2.4.0.dist-info/RECORD
