Metadata-Version: 2.1
Name: micropython-pycayennelpp
Version: 2.4.0
Summary: Encoder and Decoder for CayenneLLP
Home-page: http://github.com/smlng/pycayennelpp
Author: smlng
Author-email: s@mlng.net
License: MIT
Keywords: cayenne lpp iot lora lorawan ttn
Platform: UNKNOWN
Classifier: Development Status :: 5 - Production/Stable
Classifier: Intended Audience :: Developers
Classifier: License :: OSI Approved :: MIT License
Classifier: Programming Language :: Python :: Implementation :: MicroPython
License-File: LICENSE
